{

	"today": {
		"one": {
			"name": "wagerfield/parallax",
			"watchers": 208,
			"stargazers": 3357,
			"forks": 304,
			"pulls": 3,
			"contributors": 10
		},

		"two": {
			"name": "mduvall/grande.js",
			"watchers": 29,
			"stargazers": 759,
			"forks": 25,
			"pulls": 8,
			"contributors": 4
		},

		"three": {
			"name": "isnowfy/pydown" ,
			"watchers": 26,
			"stargazers": 449,
			"forks": 34,
			"pulls": 4,
			"contributors": 4
		},

		"four": {
			"name": "square/maximum-awesome",
			"watchers": 240,
			"stargazers": 2411,
			"forks": 523,
			"pulls": 35,
			"contributors": 13
		},

		"five": {
			"name": "vigneshwaranr/bd",
			"watchers": 27,
			"stargazers": 427,
			"forks": 31,
			"pulls": 8,
			"contributors": 2
		}

	}

}